{"1":"Больная жалуется на головную боль, головокружени, не уточняет, анамнез не дает","2":"Со слов родственника около 21:30 16.02.21г. была обнаружена лежащей в рвотных массах (съеденным), на диване, с нарушенной речью, заговаривающейся, с повышением АД до 160\/100 мм.рт.ст., ничего до приезда ОНМП не давали.Со слов дочери страдает гипертонией (амлодипин) и деменцией, стоит на учете у психиатра, травм и операций не было. Эпиданамнез без особенностей, за пределы Москвы и РФ не выезжала, сезонные прививки отрицает. Аллергию родственник отрицает. Менопауза с 50 лет. ЕМИАС, МГФОМС- не доступен","3":"ср.тяжести","4":"ясное","5":"15","6":"пассивное","7":"","8":"сухие","9":"","10":"обычной окраски","11":"","12":"","13":"","14":"","15":"","16":" нет","17":" чистый","18":" не увеличены","19":" не увеличены","20":" нет","21":" нет","22":"36.6","23":"16","24":"эксператорная","25":"нет","26":"везикулярное","27":"","28":"","29":"","30":"","31":"","32":"По всем полям","33":"сухие","34":"","35":"","36":"Нет","37":"","38":"","39":"","40":"Нет","41":"","42":"","43":"Нет","44":"легочный","45":"","46":"","47":"","48":"","49":"по всем полям","50":"","51":"","52":"","53":"отсутствует","54":" нет","55":"95","56":"ритмичный","57":"удовлетворительное","58":"95","59":"","60":"170\/100","61":"120\/80","62":"180\/100","63":"приглушены","64":"систолический","65":"","66":"верхушке","67":" нет","68":"нет","69":"I","70":"аорте","71":"влажный","72":"чистый, отклонен вправо","73":"правильная","74":"мягкий","75":"Не напряжен","76":"безболезненный","77":"Во всех отделах","78":"Ортнера","79":" отрицательные","80":" выслушивается","81":" не увеличена","82":" не пальпируется","83":" нет","84":" регулярный,  оформлен ","85":"","86":"беспокойное","87":"","88":" контактен","89":"сохранена D = S","90":"дизартрия","91":"","92":"OD = OS","93":"обычные","94":" живая","95":" мелкоразмашистый влево","96":" сглаженность носогубной складки справа","97":"","98":"Нет","99":"Девиация языка влево, сила рук D>S","100":"Не выполняет по тяжести состояния","101":"Непроизвольное мочеиспускание однократное","102":" отрицательный с обеих сторон","103":"55","104":"160","105":"","106":"сахар крови: 8,4 ммоль\/л","107":"95%","108":"ЭКГ(16.02.21 г. 23:35) ритм синусовый, правильный с ЧСС 95 в мин, ЭОС не отклонена, ST- изолиния, гипертрофия миокарда левого желудочка. ЭКГ для анализа не предоставлено. Данных за острую коронарную патологию нет.","109":" расспрос;  расспрос родственников;","110":"Установлен в\/в катетер в правую кубитальную вену;  Sol.Magnesii sulfatis 250mg\/ml-10ml + Sol.Natrii chloridi 0,9%-250ml в\/в капельно со скоростью 60 кап в мин;  Tab. Glicini 500mg сублингвально;","111":"Вызов бригады СМП","112":"","113":"Больная сдана в состоянии средней степени тяжести, АД 150\/80 мм.рт.ст., ЧСС 93 в мин, пульс 93 в мин, ЧД 18 в мин, ","114":"","115":" нет","116":"10","117":"1","118":"1","119":"1","120":"1","121":"1","122":"1","123":"1","124":"0","125":"1","126":"1","127":"1","128":"1","129":"1","130":"1","131":"0","132":"","order":"Инсульт, посмотреть","date":"","status":"template","comment":""}