{"1":"На недомогание, подъем температуры до 37,3, заболел остро, болен первый день, связывает с переохлаждением, самостоятельно не лечился, за мед помощью не обращался","2":"Эпид анамнез: контакт с ковид 19 отрицает, из Москвы не выезжал, сезонные прививки отрицает. В анамнезе: гипертоническая болезнь, хроническая ишемия головного мозга,  ХОБЛ (спирива). Крупноклеточная диффузная неходжкинская лимфома (крайняя химиотерапия авг 2019) - наблюдается онкологом, гематологом и пульмонологом  , оперирован по поводу аденомы предстательной железы в авг 2019 г. травмы отрицает, аллергии нет. ЕМИАС, МГФОМС -I11.9, I67.8,I71.4, J44.8, D28.1,H40.1,C83.3, N83.3, I83.9","3":"ср.тяжести","4":"ясное","5":"15","6":"активное","7":"","8":"сухие","9":"","10":"обычной окраски","11":"","12":"","13":"","14":"","15":"","16":" нет","17":"гиперемирован","18":" не увеличены,чистые","19":" не увеличены,безболезненные, неспаяны","20":" нет","21":" нет","22":"36.6","23":"20","24":"смешанная","25":"нет","26":"везикулярное","27":"жесткое","28":"","29":"","30":"ослаблено","31":"","32":"Равномерно в нижних отделах","33":"сухие","34":"свистящие","35":"","36":"Нет","37":"","38":"","39":"","40":"Нет","41":"","42":"","43":"Нет","44":"легочный","45":"","46":"","47":"","48":"","49":"По всему объему","50":"сухой","51":"","52":"","53":"отсутствует","54":" нет","55":"80","56":"ритмичный","57":"удовлетворительное","58":"80","59":"","60":"170\/90","61":"130\/80","62":"170\/80","63":"звучные","64":"систолический","65":"","66":"Верхушке","67":" нет","68":"нет","69":"I","70":"Аорте","71":"влажный","72":"Беловатым налетом у корня","73":"правильная","74":"мягкий","75":"Не напряжен","76":"безболезненный","77":"Во всех отделах","78":"","79":" отрицательные","80":" выслушивается","81":" не увеличена","82":" не пальпируется","83":" нет","84":" регулярный, оформлен ","85":"спокойное","86":"","87":"","88":" контактен","89":"сохранена D = S","90":"внятная","91":"","92":"OD = OS","93":"обычные","94":" живая","95":" нет","96":" нет","97":"","98":"Нет","99":"Нет","100":" выполняет правильно","101":" дизурии нет","102":" отрицательный с обеих сторон","103":"94","104":"182","105":"NEWS 2 балла","106":"","107":"94%","108":"ЭКГ(04.02.21 г. 23:18) ритм синусовый, правильный с ЧСС 80 в мин, ЭОС отклонена влево. ST- изолиния. Диффузные изменения в миокарде левого желудочка и по перегородной области. Данных за острую коронарную патологию нет","109":" расспрос, изучение архива ЭКГ, изучение мед. документов,долгие уговоры","110":"","111":"Отказ от вызова бригады СМП, актив в поликлинику","112":"","113":"Через 46 мин состояние удовлетворительное, АД 145\/80 мм.рт.ст. , ЧСС 76 в мин, пульс 76 в мин, ЧД 20 в мин, температура 36,6, NEWS 2 балла","114":"Антибактериальная терапия, полоскание горла","115":" нет","116":"2","117":"1","118":"1","119":"1","120":"1","121":"1","122":"0","123":"0","124":"0","125":"0","126":"0","127":"0","128":"0","129":"0","130":"0","131":"0","132":"Халат защитный, респиратор ana 1 шт","order":"102670826","date":"2021-02-04","status":"archive","comment":""}